freehub/__init__.py
freehub/apis.py
freehub/git_ops.py
freehub/path.py
freehub/utils.py
freehub/clitools/__init__.py
freehub/clitools/cli.py
freehub/clitools/fpyrun.py
freehub/clitools/frun.py
freehub/clitools/fsh.py
freehub-0.1.3.5.dist-info/LICENSE
freehub-0.1.3.5.dist-info/METADATA
freehub-0.1.3.5.dist-info/WHEEL
freehub-0.1.3.5.dist-info/entry_points.txt
freehub-0.1.3.5.dist-info/top_level.txt
freehub-0.1.3.5.dist-info/RECORD
