Metadata-Version: 2.1
Name: freehub
Version: 0.1.3.5
Summary: With one command, upload file to freehub , or download from freehub. Easy to use. 
Home-page: http://github.com/Peiiii/freehub
Author: WangPei
Author-email: 1535376447@qq.com
License: UNKNOWN
Platform: UNKNOWN
Classifier: Programming Language :: Python :: 3
Classifier: License :: OSI Approved :: MIT License
Classifier: Operating System :: OS Independent
Requires-Python: >=3.0
Requires-Dist: dulwich (==0.19.15)
Requires-Dist: fire
Requires-Dist: six (>=1.15.0)
